CMakeLists.txt
LICENSE
MANIFEST.in
README.rst
pyproject.toml
requirements.txt
setup.py
FFATS/Base.py
FFATS/Feature.py
FFATS/FeatureFunctionLib.py
FFATS/PreprocessLC.py
FFATS/__init__.py
FFATS/alignLC.py
FFATS/featureFunction.py
FFATS/import_lc_cluster.py
FFATS/import_lightcurve.py
FFATS/lomb.py
FFATS/test_library.py
FFATS/pybind11_CAR/fast_CAR.cpp
ffats.egg-info/PKG-INFO
ffats.egg-info/SOURCES.txt
ffats.egg-info/dependency_links.txt
ffats.egg-info/not-zip-safe
ffats.egg-info/requires.txt
ffats.egg-info/top_level.txt